{"cookies": [{"name": "_ga", "value": "GA1.1.1067292591.1762240151", "domain": ".340bpriceguide.net", "path": "/", "expires": 1796800218.493089, "httpOnly": false, "secure": false, "sameSite": "Lax"}, {"name": "779c33247f23531be79d1881a78e8629", "value": "m9qj3fna35d7cmsviuq0p90gb5", "domain": "www.340bpriceguide.net", "path": "/", "expires": -1, "httpOnly": true, "secure": true, "sameSite": "Lax"}, {"name": "joomla_user_state", "value": "logged_in", "domain": "www.340bpriceguide.net", "path": "/", "expires": -1, "httpOnly": true, "secure": true, "sameSite": "Lax"}, {"name": "_ga_F28ZDW9C20", "value": "GS2.1.s1762240151$o1$g1$t1762240219$j59$l0$h0", "domain": ".340bpriceguide.net", "path": "/", "expires": 1796800219.493132, "httpOnly": false, "secure": false, "sameSite": "Lax"}], "origins": []}